dirtree/__init__.py
dirtree/__main__.py
dirtree/console.py
ascii_dirtree-1.1.0.dist-info/METADATA
ascii_dirtree-1.1.0.dist-info/WHEEL
ascii_dirtree-1.1.0.dist-info/entry_points.txt
ascii_dirtree-1.1.0.dist-info/licenses/LICENSE
ascii_dirtree-1.1.0.dist-info/RECORD
