Metadata-Version: 2.1
Name: ascii-dirtree
Version: 1.1.0
Summary: Small CLI app to print out a pretty ascii tree of a directory.
Project-URL: Homepage, https://github.com/juso40/dirtree
Project-URL: Bug Tracker, https://github.com/juso40/dirtree/issues
Author: Justin Sostmann
License-File: LICENSE
Classifier: Environment :: Console
Classifier: License :: OSI Approved :: MIT License
Classifier: Operating System :: OS Independent
Classifier: Programming Language :: Python :: 3
Requires-Python: >=3.9
